[{"Id":1,"Name":"The Catcher in the Rye","Author":"J.D. Salinger","PublicationYear":1951,"Genre":"Fiction","Language":"English","Description":"A classic novel about teenage angst and rebellion.","AddedBy":123,"AddedDate":"2024-04-13T12:00:00"},{"Id":2,"Name":"1984","Author":"George Orwell","PublicationYear":1949,"Genre":"Science Fiction","Language":"English","Description":"A dystopian novel depicting a totalitarian regime.","AddedBy":456,"AddedDate":"2024-04-13T13:30:00"},{"Id":3,"Name":"The Hobbit","Author":"J.R.R. Tolkien","PublicationYear":1937,"Genre":"Fantasy","Language":"English","Description":"An adventurous tale of Bilbo Baggins and his journey.","AddedBy":789,"AddedDate":"2024-04-12T09:45:00"},{"Id":4,"Name":"To Kill a Mockingbird","Author":"Harper Lee","PublicationYear":1960,"Genre":"Fiction","Language":"English","Description":"A powerful story of racial injustice and moral growth.","AddedBy":234,"AddedDate":"2024-04-12T15:20:00"},{"Id":0,"Name":"sfdg","Author":"wrt","PublicationYear":null,"Genre":"dsfg","Language":"sdfg","Description":"sdfg","AddedBy":0,"AddedDate":"0001-01-01T00:00:00"},{"Id":0,"Name":"sdf","Author":"sdfsdf","PublicationYear":432,"Genre":"asfd","Language":"2234","Description":"234","AddedBy":0,"AddedDate":"0001-01-01T00:00:00"},{"Id":0,"Name":"Ufaz","Author":"Vazeh","PublicationYear":2016,"Genre":"horror","Language":"francais","Description":"Kazarma","AddedBy":0,"AddedDate":"0001-01-01T00:00:00"},{"Id":0,"Name":"test","Author":"tesstov","PublicationYear":2133,"Genre":"dsfhsjdf","Language":"Azerbaycan","Description":"hello world","AddedBy":0,"AddedDate":"0001-01-01T00:00:00"},{"Id":0,"Name":"test","Author":"sdfsdf","PublicationYear":null,"Genre":"sdfsdf","Language":"sdfsdf","Description":"sdfsdf","AddedBy":0,"AddedDate":"0001-01-01T00:00:00"},{"Id":0,"Name":"clara","Author":"asdgsafg","PublicationYear":-236,"Genre":"svoloch","Language":"francais","Description":"tatoo","AddedBy":0,"AddedDate":"0001-01-01T00:00:00"},{"Id":0,"Name":"adsfas","Author":"asdfasdf","PublicationYear":null,"Genre":"asdf","Language":"sadfwq","Description":"rtwqrt","AddedBy":0,"AddedDate":"0001-01-01T00:00:00"},{"Id":0,"Name":"aaaaaaaaaaa","Author":"aaaaaaaaaaaaa","PublicationYear":null,"Genre":"aaaaaaaaaaaaaaaaaaaaaaaaaaaa","Language":"aaaaaaaaaaaaaaaaaaaaaaaaaaaaaa","Description":"aaaaaaaaaaaaaaaa","AddedBy":0,"AddedDate":"0001-01-01T00:00:00"},{"Id":0,"Name":"asdfas","Author":"sadf","PublicationYear":null,"Genre":"adfaf","Language":"fsadfasdfasfdsa","Description":"asdfas","AddedBy":0,"AddedDate":"0001-01-01T00:00:00"},{"Id":0,"Name":"\u0444\u0444\u0444\u0444\u0444\u0444\u0444\u0444\u0444\u0444\u0444\u0444","Author":"\u0444\u0444\u0444\u0444\u0444\u0444\u0444\u0444\u0444\u0444\u0444\u0444","PublicationYear":null,"Genre":"\u0444\u0444\u0444\u0444\u0444\u0444\u0444\u0444\u0444\u0444\u0444\u0444\u0444","Language":"\u0444\u0444\u0444\u0444\u0444\u0444\u0444\u0444\u0444\u0444\u0444\u0444\u0444\u0444\u0444\u0444\u0444\u0444\u0444\u0444\u0444\u0444\u0444\u0444\u0444\u0444\u0444\u0444\u0444\u0444\u0444\u0444\u0444\u0444","Description":"\u0444\u0444\u0444\u0444\u0444\u0444\u0444\u0444\u0444\u0444\u0444\u0444\u0444","AddedBy":0,"AddedDate":"0001-01-01T00:00:00"},{"Id":0,"Name":"sadf","Author":"sadf","PublicationYear":null,"Genre":"sdf","Language":"fd","Description":"sadf","AddedBy":0,"AddedDate":"0001-01-01T00:00:00"},{"Id":0,"Name":"AAAAAAAA","Author":"AAAAAAAAAAAAA","PublicationYear":null,"Genre":"AAAAAAAAAAAAAA","Language":"AAAAAAAAAAAAAAAAAAAAAAAAAAAAAAAAAAAAA","Description":"AAAAAAAAAAAAAAAAAA","AddedBy":0,"AddedDate":"0001-01-01T00:00:00"},{"Id":0,"Name":"sdf","Author":"sdfsd","PublicationYear":null,"Genre":"sadfsas","Language":"adfasdf","Description":"sadfas","AddedBy":0,"AddedDate":"0001-01-01T00:00:00"},{"Id":0,"Name":"aaaaaaaaaaaaaaaaaaaa","Author":"aaaaaaaaaaaaaaaa","PublicationYear":null,"Genre":"aaaaaaaaaaaaaa","Language":"aaaaaaaaaaaaaaaaaaaaaaaaaaaaaaaaaaaaaaa","Description":"aaaaaaaaaaaaaaaa","AddedBy":0,"AddedDate":"0001-01-01T00:00:00"}]